<databases>
	<database>
		<name>data</name>
		<description>Confirmed, controversial and retracted exoplanets</description>
		<num>915</num>
		<date>2013-05-25</date>
		<size>881984</size>
		<sizecompressed>95333</sizecompressed>
		<hash>315d339ace1ef5174f48f70a79ad17a6</hash>
	</database>
	<database>
		<name>datakepler</name>
		<description>Kepler Objects of Interest (unconfirmed)</description>
		<num>2740</num>
		<date>2013-05-25</date>
		<size>2065268</size>
		<sizecompressed>120364</sizecompressed>
		<hash>1e0055bc5025b6400e86168652c9d2c7</hash>
	</database>
</databases>
