<databases>
	<database>
		<name>data</name>
		<description>Confirmed, controversial and retracted exoplanets</description>
		<num>3399</num>
		<date>2016-05-10</date>
		<size>3440393</size>
		<sizecompressed>277406</sizecompressed>
		<hash>2b043b50ee8ae1a3dd9e80670c6ed520</hash>
	</database>
	<database>
		<name>datakepler</name>
		<description>Kepler Objects of Interest (unconfirmed)</description>
		<num>3215</num>
		<date>2016-05-10</date>
		<size>2447330</size>
		<sizecompressed>142426</sizecompressed>
		<hash>2cfdc0d42d18af6efb5bbe5471a77db7</hash>
	</database>
</databases>
