<databases>
	<database>
		<name>data</name>
		<description>Confirmed, controversial and retracted exoplanets</description>
		<num>916</num>
		<date>2013-06-03</date>
		<size>886513</size>
		<sizecompressed>96402</sizecompressed>
		<hash>f9b16eccdc5faea35d2ca14e6e3e6236</hash>
	</database>
	<database>
		<name>datakepler</name>
		<description>Kepler Objects of Interest (unconfirmed)</description>
		<num>2740</num>
		<date>2013-06-03</date>
		<size>2065268</size>
		<sizecompressed>120365</sizecompressed>
		<hash>d6e8a61bc660039c249b1a5ee872f209</hash>
	</database>
</databases>
