<databases>
	<database>
		<name>data</name>
		<description>Confirmed, controversial and retracted exoplanets</description>
		<num>2075</num>
		<date>2015-11-12</date>
		<size>2210781</size>
		<sizecompressed>208423</sizecompressed>
		<hash>94b53856d138a3bbc43811a05b17a111</hash>
	</database>
	<database>
		<name>datakepler</name>
		<description>Kepler Objects of Interest (unconfirmed)</description>
		<num>3215</num>
		<date>2015-11-12</date>
		<size>2447330</size>
		<sizecompressed>142426</sizecompressed>
		<hash>6cfbed2294e75f094efae2f38668b34e</hash>
	</database>
</databases>
