<databases>
	<database>
		<name>data</name>
		<description>Confirmed, controversial and retracted exoplanets</description>
		<num>3615</num>
		<date>2017-12-02</date>
		<size>3618465</size>
		<sizecompressed>402146</sizecompressed>
		<hash>f2b4d7e2951319ec055c4da2f216613e</hash>
	</database>
	<database>
		<name>datakepler</name>
		<description>Kepler Objects of Interest (unconfirmed)</description>
		<num>3215</num>
		<date>2017-12-02</date>
		<size>2447330</size>
		<sizecompressed>171159</sizecompressed>
		<hash>a9022907c209c83af0716639f10df1c4</hash>
	</database>
</databases>
