<databases>
	<database>
		<name>data</name>
		<description>Confirmed, controversial and retracted exoplanets</description>
		<num>861</num>
		<date>2012-11-26</date>
		<size>761293</size>
		<sizecompressed>77711</sizecompressed>
		<hash>ab2547a29ab63071e9df87e1efc07910</hash>
	</database>
	<database>
		<name>datakepler</name>
		<description>Kepler Objects of Interest (unconfirmed)</description>
		<num>2314</num>
		<date>2012-11-26</date>
		<size>1777396</size>
		<sizecompressed>133627</sizecompressed>
		<hash>9fad774e418a76107cd27640ac82853f</hash>
	</database>
</databases>
