<databases>
	<database>
		<name>systems</name>
		<description>Confirmed, controversial and retracted exoplanets</description>
		<num>941</num>
		<systems>712</systems>
		<date>2013-08-05</date>
		<size>1029882</size>
		<sizecompressed>140412</sizecompressed>
		<hash>c0e72135b25d6e5f83f3377c47d88cde</hash>
	</database>
	<database>
		<name>systemskepler</name>
		<description>Kepler Objects of Interest (unconfirmed)</description>
		<num>3277</num>
		<systems>2485</systems>
		<date>2013-08-05</date>
		<size>3238928</size>
		<sizecompressed>288142</sizecompressed>
		<hash>5b0cd227425b81d313b6247054af0db8</hash>
	</database>
</databases>
