<planet>
	<id_exoplaneteu>KOI-4120 b</id_exoplaneteu>
	<name>KOI-4120 b</name>
	<name>KOI-4120 01</name>
	<id>KOI-4120 b</id>
	<discoverymethod />
	<properties>
		<mass />
		<radius>0.16403</radius>
		<orbit>
			<period>110.464100000000</period>
			<semimajoraxis>0.4710620</semimajoraxis>
			<eccentricity />
			<inclination />
		</orbit>
	</properties>
	<star>
		<spectraltype />
		<mass />
		<radius>1.0650</radius>
		<metallicity />
		<temperature>419.0</temperature>
		<rightascension>19 08 09</rightascension>
		<declination>+46 28 54</declination>
		<angulardistance />
		<distance />
		<magV />
		<magI />
		<magH />
		<magJ />
		<magK />
	</star>
	<multiplicity>1</multiplicity>
	<discoveryyear />
	<lastupdate />
	<description>This is a Kepler Object of Interest from the Q1-Q12 dataset. It has been flagged as a possible transit event but has not been confirmed to be a planet yet.</description>
	<new />
	<image />
	<imagedescription />
	<list>Kepler Objects of Interest</list>
</planet>
