<planet>
	<id_exoplaneteu>KOI-4344 b</id_exoplaneteu>
	<name>KOI-4344 b</name>
	<name>KOI-4344 01</name>
	<id>KOI-4344 b</id>
	<discoverymethod />
	<properties>
		<mass />
		<radius>0.34630</radius>
		<orbit>
			<period>4.319789000000</period>
			<semimajoraxis>0.0651219</semimajoraxis>
			<eccentricity />
			<inclination />
		</orbit>
	</properties>
	<star>
		<spectraltype />
		<mass />
		<radius>5.2370</radius>
		<metallicity />
		<temperature>2242.0</temperature>
		<rightascension>19 54 04</rightascension>
		<declination>+39 55 27</declination>
		<angulardistance />
		<distance />
		<magV />
		<magI />
		<magH />
		<magJ />
		<magK />
	</star>
	<multiplicity>1</multiplicity>
	<discoveryyear />
	<lastupdate />
	<description />
	<new />
	<image />
	<imagedescription />
	<list>Kepler Objects of Interest</list>
</planet>
