<planet>
	<id_exoplaneteu>KOI-0730 b</id_exoplaneteu>
	<name>KOI-0730 b</name>
	<name>KOI-0730 01</name>
	<id>KOI-0730 b</id>
	<discoverymethod />
	<properties>
		<mass />
		<radius>0.27339</radius>
		<orbit>
			<period>14.788400</period>
			<semimajoraxis>0.116</semimajoraxis>
			<eccentricity />
			<inclination />
		</orbit>
	</properties>
	<star>
		<spectraltype />
		<mass />
		<radius>1.03</radius>
		<metallicity />
		<temperature>5832.00</temperature>
		<rightascension>19 53 16</rightascension>
		<declination>+47 16 46</declination>
		<angulardistance />
		<distance>1385.85</distance>
		<magV />
		<magI />
		<magH />
		<magJ />
		<magK />
	</star>
	<multiplicity>4</multiplicity>
	<discoveryyear />
	<lastupdate />
	<description>This is a Kepler Object of Interest from the Q1-Q8 dataset. It has been flagged as a possible transit event but has not been confirmed to be a planet yet.</description>
	<new />
	<image />
	<imagedescription />
	<list>Kepler Objects of Interest</list>
</planet>
