<planet>
	<id_exoplaneteu>KOI-4755 b</id_exoplaneteu>
	<name>KOI-4755 b</name>
	<name>KOI-4755 01</name>
	<id>KOI-4755 b</id>
	<discoverymethod />
	<properties>
		<mass />
		<radius>0.13670</radius>
		<orbit>
			<period>3.743257000000</period>
			<semimajoraxis>0.0451660</semimajoraxis>
			<eccentricity />
			<inclination />
		</orbit>
	</properties>
	<star>
		<spectraltype />
		<mass />
		<radius>0.7860</radius>
		<metallicity />
		<temperature>1001.0</temperature>
		<rightascension>18 42 39</rightascension>
		<declination>+47 06 50</declination>
		<angulardistance />
		<distance />
		<magV />
		<magI />
		<magH />
		<magJ />
		<magK />
	</star>
	<multiplicity>1</multiplicity>
	<discoveryyear />
	<lastupdate />
	<description>This is a Kepler Object of Interest from the Q1-Q12 dataset. It has been flagged as a possible transit event but has not been confirmed to be a planet yet.</description>
	<new />
	<image />
	<imagedescription />
	<list>Kepler Objects of Interest</list>
</planet>
