<planet>
	<id_exoplaneteu>KOI-4504 b</id_exoplaneteu>
	<name>KOI-4504 b</name>
	<name>KOI-4504 01</name>
	<id>KOI-4504 b</id>
	<discoverymethod />
	<properties>
		<mass />
		<radius>0.13670</radius>
		<orbit>
			<period>4.130403000000</period>
			<semimajoraxis>0.0499264</semimajoraxis>
			<eccentricity />
			<inclination />
		</orbit>
	</properties>
	<star>
		<spectraltype />
		<mass />
		<radius>0.8540</radius>
		<metallicity />
		<temperature>964.5</temperature>
		<rightascension>19 25 10</rightascension>
		<declination>+41 54 46</declination>
		<angulardistance />
		<distance />
		<magV />
		<magI />
		<magH />
		<magJ />
		<magK />
	</star>
	<multiplicity>2</multiplicity>
	<discoveryyear />
	<lastupdate />
	<description />
	<new />
	<image />
	<imagedescription />
	<list>Kepler Objects of Interest</list>
</planet>
