<planet>
	<id_exoplaneteu>KOI-4125 b</id_exoplaneteu>
	<name>KOI-4125 b</name>
	<name>KOI-4125 01</name>
	<id>KOI-4125 b</id>
	<discoverymethod />
	<properties>
		<mass />
		<radius>0.07655</radius>
		<orbit>
			<period>1.111434400000</period>
			<semimajoraxis>0.0223103</semimajoraxis>
			<eccentricity />
			<inclination />
		</orbit>
	</properties>
	<star>
		<spectraltype />
		<mass />
		<radius>1.3330</radius>
		<metallicity />
		<temperature>2212.0</temperature>
		<rightascension>19 42 26</rightascension>
		<declination>+45 29 04</declination>
		<angulardistance />
		<distance />
		<magV />
		<magI />
		<magH />
		<magJ />
		<magK />
	</star>
	<multiplicity>1</multiplicity>
	<discoveryyear />
	<lastupdate />
	<description />
	<new />
	<image />
	<imagedescription />
	<list>Kepler Objects of Interest</list>
</planet>
