<planet>
	<id_exoplaneteu>KOI-4619 b</id_exoplaneteu>
	<name>KOI-4619 b</name>
	<name>KOI-4619 01</name>
	<id>KOI-4619 b</id>
	<discoverymethod />
	<properties>
		<mass />
		<radius>0.25516</radius>
		<orbit>
			<period>62.379970000000</period>
			<semimajoraxis>0.3445770</semimajoraxis>
			<eccentricity />
			<inclination />
		</orbit>
	</properties>
	<star>
		<spectraltype />
		<mass />
		<radius>1.7920</radius>
		<metallicity />
		<temperature>678.0</temperature>
		<rightascension>19 09 35</rightascension>
		<declination>+43 24 51</declination>
		<angulardistance />
		<distance />
		<magV />
		<magI />
		<magH />
		<magJ />
		<magK />
	</star>
	<multiplicity>1</multiplicity>
	<discoveryyear />
	<lastupdate />
	<description />
	<new />
	<image />
	<imagedescription />
	<list>Kepler Objects of Interest</list>
</planet>
