<planet>
	<id_exoplaneteu>KOI-4526 b</id_exoplaneteu>
	<name>KOI-4526 b</name>
	<name>KOI-4526 01</name>
	<id>KOI-4526 b</id>
	<discoverymethod />
	<properties>
		<mass />
		<radius>0.19137</radius>
		<orbit>
			<period>30.540060000000</period>
			<semimajoraxis>0.1956090</semimajoraxis>
			<eccentricity />
			<inclination />
		</orbit>
	</properties>
	<star>
		<spectraltype />
		<mass />
		<radius>0.9810</radius>
		<metallicity />
		<temperature>604.0</temperature>
		<rightascension>19 43 52</rightascension>
		<declination>+38 52 01</declination>
		<angulardistance />
		<distance />
		<magV />
		<magI />
		<magH />
		<magJ />
		<magK />
	</star>
	<multiplicity>1</multiplicity>
	<discoveryyear />
	<lastupdate />
	<description />
	<new />
	<image />
	<imagedescription />
	<list>Kepler Objects of Interest</list>
</planet>
