<planet>
	<id_exoplaneteu>KOI-3827 c</id_exoplaneteu>
	<name>KOI-3827 c</name>
	<name>KOI-3827 02</name>
	<id>KOI-3827 c</id>
	<discoverymethod />
	<properties>
		<mass />
		<radius>1.18469</radius>
		<orbit>
			<period>389.280800000000</period>
			<semimajoraxis>1.0492300</semimajoraxis>
			<eccentricity />
			<inclination />
		</orbit>
	</properties>
	<star>
		<spectraltype />
		<mass />
		<radius>1.0000</radius>
		<metallicity />
		<temperature>271.0</temperature>
		<rightascension>19 42 55</rightascension>
		<declination>+40 15 38</declination>
		<angulardistance />
		<distance />
		<magV />
		<magI />
		<magH />
		<magJ />
		<magK />
	</star>
	<multiplicity>2</multiplicity>
	<discoveryyear />
	<lastupdate />
	<description />
	<new />
	<image />
	<imagedescription />
	<list>Kepler Objects of Interest</list>
</planet>
