<planet>
	<id_exoplaneteu>KOI-4355 f</id_exoplaneteu>
	<name>KOI-4355 f</name>
	<name>KOI-4355 05</name>
	<id>KOI-4355 f</id>
	<discoverymethod />
	<properties>
		<mass />
		<radius>0.24605</radius>
		<orbit>
			<period>72.568400000000</period>
			<semimajoraxis>0.3405620</semimajoraxis>
			<eccentricity />
			<inclination />
		</orbit>
	</properties>
	<star>
		<spectraltype />
		<mass />
		<radius>1.0000</radius>
		<metallicity />
		<temperature>548.9</temperature>
		<rightascension>19 36 49</rightascension>
		<declination>+39 40 48</declination>
		<angulardistance />
		<distance />
		<magV />
		<magI />
		<magH />
		<magJ />
		<magK />
	</star>
	<multiplicity>5</multiplicity>
	<discoveryyear />
	<lastupdate />
	<description />
	<new />
	<image />
	<imagedescription />
	<list>Kepler Objects of Interest</list>
</planet>
