<planet>
	<id_exoplaneteu>KOI-0227 b</id_exoplaneteu>
	<name>KOI-0227 b</name>
	<name>KOI-0227 01</name>
	<id>KOI-0227 b</id>
	<discoverymethod />
	<properties>
		<mass />
		<radius>0.26792</radius>
		<orbit>
			<period>17.660113000000</period>
			<semimajoraxis>0.1180000</semimajoraxis>
			<eccentricity />
			<inclination />
		</orbit>
	</properties>
	<star>
		<spectraltype />
		<mass />
		<radius>0.6330</radius>
		<metallicity />
		<temperature>4633.00</temperature>
		<rightascension>18 57 24</rightascension>
		<declination>+41 31 09</declination>
		<angulardistance />
		<distance>327.32</distance>
		<magV />
		<magI />
		<magH />
		<magJ />
		<magK />
	</star>
	<multiplicity>1</multiplicity>
	<discoveryyear />
	<lastupdate />
	<description>This is a Kepler Object of Interest from the Q1-Q12 dataset. It has been flagged as a possible transit event but has not been confirmed to be a planet yet.</description>
	<new />
	<image />
	<imagedescription />
	<list>Kepler Objects of Interest</list>
</planet>
