<planet>
	<id_exoplaneteu>KOI-3669 b</id_exoplaneteu>
	<name>KOI-3669 b</name>
	<name>KOI-3669 01</name>
	<id>KOI-3669 b</id>
	<discoverymethod />
	<properties>
		<mass />
		<radius>3.65432</radius>
		<orbit>
			<period>1.731784650000</period>
			<semimajoraxis>0.0286364</semimajoraxis>
			<eccentricity />
			<inclination />
		</orbit>
	</properties>
	<star>
		<spectraltype />
		<mass />
		<radius>1.0300</radius>
		<metallicity />
		<temperature>1462.9</temperature>
		<rightascension>19 17 01</rightascension>
		<declination>+39 24 35</declination>
		<angulardistance />
		<distance />
		<magV />
		<magI />
		<magH />
		<magJ />
		<magK />
	</star>
	<multiplicity>1</multiplicity>
	<discoveryyear />
	<lastupdate />
	<description />
	<new />
	<image />
	<imagedescription />
	<list>Kepler Objects of Interest</list>
</planet>
