<planet>
	<id_exoplaneteu>KOI-1925 b</id_exoplaneteu>
	<name>KOI-1925 b</name>
	<name>KOI-1925 01</name>
	<id>KOI-1925 b</id>
	<discoverymethod />
	<properties>
		<mass />
		<radius>0.10207</radius>
		<orbit>
			<period>68.958030000000</period>
			<semimajoraxis>0.3160000</semimajoraxis>
			<eccentricity />
			<inclination />
		</orbit>
	</properties>
	<star>
		<spectraltype />
		<mass />
		<radius>0.9470</radius>
		<metallicity />
		<temperature>5365.00</temperature>
		<rightascension>19 34 43</rightascension>
		<declination>+46 51 09</declination>
		<angulardistance />
		<distance>71.08</distance>
		<magV />
		<magI />
		<magH />
		<magJ />
		<magK />
	</star>
	<multiplicity>1</multiplicity>
	<discoveryyear />
	<lastupdate />
	<description>This is a Kepler Object of Interest from the Q1-Q12 dataset. It has been flagged as a possible transit event but has not been confirmed to be a planet yet.</description>
	<new />
	<image />
	<imagedescription />
	<list>Kepler Objects of Interest</list>
</planet>
