<planet>
	<id_exoplaneteu>KOI-3498 b</id_exoplaneteu>
	<name>KOI-3498 b</name>
	<name>KOI-3498 01</name>
	<id>KOI-3498 b</id>
	<discoverymethod />
	<properties>
		<mass />
		<radius>0.30984</radius>
		<orbit>
			<period>43.799610000000</period>
			<semimajoraxis>0.2705310</semimajoraxis>
			<eccentricity />
			<inclination />
		</orbit>
	</properties>
	<star>
		<spectraltype />
		<mass />
		<radius>2.7090</radius>
		<metallicity />
		<temperature>770.0</temperature>
		<rightascension>19 43 17</rightascension>
		<declination>+44 47 45</declination>
		<angulardistance />
		<distance />
		<magV />
		<magI />
		<magH />
		<magJ />
		<magK />
	</star>
	<multiplicity>1</multiplicity>
	<discoveryyear />
	<lastupdate />
	<description />
	<new />
	<image />
	<imagedescription />
	<list>Kepler Objects of Interest</list>
</planet>
