<planet>
	<id_exoplaneteu>HD 143105 b</id_exoplaneteu>
	<name>HD 143105 b</name>
	<id>HD 143105 b</id>
	<discoverymethod>RV</discoverymethod>
	<properties>
		<mass>1.21</mass>
		<radius />
		<orbit>
			<period>2.1974</period>
			<semimajoraxis>0.0379</semimajoraxis>
			<eccentricity />
			<inclination />
			<periastron />
			<longitude />
			<ascendingnode />
		</orbit>
	</properties>
	<star>
		<spectraltype>F5</spectraltype>
		<mass>1.51</mass>
		<radius />
		<metallicity>0.15</metallicity>
		<distance>49.95</distance>
		<temperature>6380</temperature>
		<rightascension>15 53 36.5585</rightascension>
		<declination>+68 43 12.413</declination>
		<angulardistance />
		<magV>6.75</magV>
		<magI />
		<magH />
		<magJ />
		<magK />
	</star>
	<multiplicity>1</multiplicity>
	<discoveryyear>2016</discoveryyear>
	<lastupdate>17/12/09</lastupdate>
	<description>HD 143105 b is one of a batch of twelve planets identified by the SOPHIE search for northern extrasolar planets.</description>
	<new />
	<image />
	<imagedescription />
	<list>Confirmed planets</list>
</planet>
