<planet>
	<id_exoplaneteu>HD 191806 b</id_exoplaneteu>
	<name>HD 191806 b</name>
	<id>HD 191806 b</id>
	<discoverymethod>RV</discoverymethod>
	<properties>
		<mass>8.52</mass>
		<radius />
		<orbit>
			<period>1606.3</period>
			<semimajoraxis>2.8</semimajoraxis>
			<eccentricity>0.259</eccentricity>
			<inclination />
			<periastron />
			<longitude />
			<ascendingnode />
		</orbit>
	</properties>
	<star>
		<spectraltype />
		<mass>1.14</mass>
		<radius />
		<metallicity>0.3</metallicity>
		<distance />
		<temperature>6010.0</temperature>
		<rightascension>20 09 28</rightascension>
		<declination>+52 16 35</declination>
		<angulardistance />
		<magV />
		<magI />
		<magH />
		<magJ />
		<magK />
	</star>
	<multiplicity>1</multiplicity>
	<discoveryyear>2016</discoveryyear>
	<lastupdate>16/04/29</lastupdate>
	<description>Data for this planet was imported from the exoplanet.eu database.</description>
	<new />
	<image />
	<imagedescription />
	<list>Confirmed planets</list>
</planet>
