<planet>
	<id_exoplaneteu>Kepler-184 b</id_exoplaneteu>
	<name>Kepler-184 b</name>
	<name>KOI-567 b</name>
	<name>KOI-567.01</name>
	<name>KIC 7445445 b</name>
	<name>KIC 7445445.01</name>
	<id>Kepler-184 b</id>
	<discoverymethod>transit</discoverymethod>
	<properties>
		<mass />
		<radius>0.21507</radius>
		<orbit>
			<period>10.687576</period>
			<semimajoraxis />
			<eccentricity />
			<inclination />
			<periastron />
			<longitude />
			<ascendingnode />
		</orbit>
	</properties>
	<star>
		<spectraltype />
		<mass>0.9700</mass>
		<radius>0.873</radius>
		<metallicity />
		<distance>727.97</distance>
		<temperature>5788</temperature>
		<rightascension>19 27 48</rightascension>
		<declination>+43 04 28</declination>
		<angulardistance />
		<magV />
		<magI />
		<magH />
		<magJ />
		<magK />
	</star>
	<multiplicity>3</multiplicity>
	<discoveryyear>2014</discoveryyear>
	<lastupdate>14/02/26</lastupdate>
	<description>Kepler-184 b has been discovered by the Kepler spacecraft and was originally classified as a planet candidate. A new statistical analysis led by a team at NASA Ames Research Center has validated the planet with more than 99 percent confidence. Although many parameters of Kepler-184 b are still unknown, the object is highly unlikely to be a false positive.</description>
	<new />
	<image />
	<imagedescription />
	<list>Confirmed planets</list>
</planet>
