<planet>
	<id_exoplaneteu>Kepler-383 b</id_exoplaneteu>
	<name>Kepler-383 b</name>
	<name>KOI-2413 b</name>
	<name>KOI-2413.01</name>
	<name>KIC 3234598 b</name>
	<name>KIC 3234598.01</name>
	<id>Kepler-383 b</id>
	<discoverymethod>transit</discoverymethod>
	<properties>
		<mass />
		<radius>0.12029</radius>
		<orbit>
			<period>12.904532</period>
			<semimajoraxis />
			<eccentricity />
			<inclination />
			<periastron />
			<longitude />
			<ascendingnode />
		</orbit>
	</properties>
	<star>
		<spectraltype />
		<mass>0.6690</mass>
		<radius>0.672</radius>
		<metallicity />
		<distance>519.82</distance>
		<temperature>4710</temperature>
		<rightascension>19 25 22</rightascension>
		<declination>+38 21 47</declination>
		<angulardistance />
		<magV />
		<magI />
		<magH />
		<magJ />
		<magK />
	</star>
	<multiplicity>2</multiplicity>
	<discoveryyear>2014</discoveryyear>
	<lastupdate>14/02/26</lastupdate>
	<description>Kepler-383 b has been discovered by the Kepler spacecraft and was originally classified as a planet candidate. A new statistical analysis led by a team at NASA Ames Research Center has validated the planet with more than 99 percent confidence. Although many parameters of Kepler-383 b are still unknown, the object is highly unlikely to be a false positive.</description>
	<new>1</new>
	<image />
	<imagedescription />
	<list>Confirmed planets</list>
</planet>
