<planet>
	<id_exoplaneteu>Kepler-125 c</id_exoplaneteu>
	<name>Kepler-125 c</name>
	<name>KOI-251 c</name>
	<name>KOI-251.02</name>
	<name>KIC 10489206 c</name>
	<name>KIC 10489206.02</name>
	<id>Kepler-125 c</id>
	<discoverymethod>transit</discoverymethod>
	<properties>
		<mass />
		<radius>0.06744</radius>
		<orbit>
			<period>5.774464</period>
			<semimajoraxis />
			<eccentricity />
			<inclination />
			<periastron />
			<longitude />
			<ascendingnode />
		</orbit>
	</properties>
	<star>
		<spectraltype />
		<mass>0.5370</mass>
		<radius>0.512</radius>
		<metallicity />
		<distance>223.85</distance>
		<temperature>3810</temperature>
		<rightascension>01 19 32</rightascension>
		<declination>+47 36 17</declination>
		<angulardistance />
		<magV />
		<magI />
		<magH />
		<magJ />
		<magK />
	</star>
	<multiplicity>2</multiplicity>
	<discoveryyear>2014</discoveryyear>
	<lastupdate>14/02/26</lastupdate>
	<description>This planet has been discovered by the Kepler spacrcraft. It was confirmed in early 2014 using a statistical framework. The false positive rate is significantly less than 1 percent.</description>
	<new>1</new>
	<image />
	<imagedescription />
	<list>Confirmed planets</list>
</planet>
