<planet>
	<id_exoplaneteu>Kepler-373 b</id_exoplaneteu>
	<name>Kepler-373 b</name>
	<name>KOI-2218 b</name>
	<name>KOI-2218.01</name>
	<name>KIC 12058204 b</name>
	<name>KIC 12058204.01</name>
	<id>Kepler-373 b</id>
	<discoverymethod>transit</discoverymethod>
	<properties>
		<mass />
		<radius>0.12394</radius>
		<orbit>
			<period>5.535309</period>
			<semimajoraxis />
			<eccentricity />
			<inclination />
			<periastron />
			<longitude />
			<ascendingnode />
		</orbit>
	</properties>
	<star>
		<spectraltype />
		<mass>0.9780</mass>
		<radius>0.845</radius>
		<metallicity />
		<distance>763.85</distance>
		<temperature>5787</temperature>
		<rightascension>01 17 10</rightascension>
		<declination>+50 35 49</declination>
		<angulardistance />
		<magV />
		<magI />
		<magH />
		<magJ />
		<magK />
	</star>
	<multiplicity>2</multiplicity>
	<discoveryyear>2014</discoveryyear>
	<lastupdate>14/02/26</lastupdate>
	<description>This planet has been discovered by the Kepler spacrcraft. It was confirmed in early 2014 using a statistical framework. The false positive rate is significantly less than 1 percent.</description>
	<new>1</new>
	<image />
	<imagedescription />
	<list>Confirmed planets</list>
</planet>
