<planet>
	<id_exoplaneteu>KOI-135 b</id_exoplaneteu>
	<name>KOI-135 b</name>
	<name>Kepler-43 b</name>
	<name>KOI-135.01</name>
	<name>GSC 03541-00075 b</name>
	<name>KIC 9818381 b</name>
	<name>2MASS J19005780+4640057 b</name>
	<id>KOI-135 b</id>
	<discoverymethod>transit</discoverymethod>
	<properties>
		<mass>3.23</mass>
		<radius>1.22</radius>
		<orbit>
			<period>3.02409309</period>
			<semimajoraxis>0.0444</semimajoraxis>
			<eccentricity>0.017</eccentricity>
			<inclination>84.57</inclination>
			<periastron>52</periastron>
			<longitude />
			<ascendingnode />
		</orbit>
	</properties>
	<star>
		<spectraltype>F8V</spectraltype>
		<mass>1.27</mass>
		<radius>1.38</radius>
		<metallicity>0.40</metallicity>
		<distance>1950</distance>
		<temperature>6050</temperature>
		<rightascension>19 00 58</rightascension>
		<declination>+46 40 06</declination>
		<angulardistance />
		<magV />
		<magI />
		<magH />
		<magJ />
		<magK />
	</star>
	<multiplicity>1</multiplicity>
	<discoveryyear>2011</discoveryyear>
	<lastupdate>15/12/03</lastupdate>
	<description />
	<new />
	<image />
	<imagedescription />
	<list>Confirmed planets</list>
</planet>
