<planet>
	<id_exoplaneteu>KOI-4307.01</id_exoplaneteu>
	<name>KOI-4307.01</name>
	<id>KOI-4307.01</id>
	<discoverymethod>transit</discoverymethod>
	<properties>
		<mass />
		<radius>0.2097</radius>
		<orbit>
			<period>160.850816</period>
			<semimajoraxis />
			<eccentricity />
			<inclination>89.38</inclination>
			<periastron />
			<longitude />
			<ascendingnode />
		</orbit>
	</properties>
	<star>
		<spectraltype />
		<mass>0.98</mass>
		<radius>1.005</radius>
		<metallicity>-0.42</metallicity>
		<distance />
		<temperature>6175</temperature>
		<rightascension>19 39 47.962</rightascension>
		<declination>+38 36 18.68</declination>
		<angulardistance />
		<magV />
		<magI />
		<magH />
		<magJ />
		<magK />
	</star>
	<multiplicity>2</multiplicity>
	<discoveryyear>2014</discoveryyear>
	<lastupdate>16/01/09</lastupdate>
	<description>KOI-4307.01 is an unconfirmed planet candidate observed orbiting KIC 3558849.</description>
	<new />
	<image />
	<imagedescription />
	<list>Controversial</list>
</planet>
