<planet>
	<id_exoplaneteu>MOA-2011-BLG-322 b</id_exoplaneteu>
	<name>MOA-2011-BLG-322 b</name>
	<name>HJD 2455773 b</name>
	<id>MOA-2011-BLG-322 b</id>
	<discoverymethod>microlensing</discoverymethod>
	<properties>
		<mass>7.8</mass>
		<radius />
		<orbit>
			<period />
			<semimajoraxis>3.6</semimajoraxis>
			<eccentricity />
			<inclination />
			<periastron />
			<longitude />
			<ascendingnode />
		</orbit>
	</properties>
	<star>
		<spectraltype>G</spectraltype>
		<mass>0.31</mass>
		<radius />
		<metallicity />
		<distance>7740</distance>
		<temperature />
		<rightascension>18 04 53</rightascension>
		<declination>-27 13 15</declination>
		<angulardistance />
		<magV />
		<magI />
		<magH />
		<magJ />
		<magK />
	</star>
	<multiplicity>1</multiplicity>
	<discoveryyear>2013</discoveryyear>
	<lastupdate>13/10/01</lastupdate>
	<description>MOA-2001-BLG-322 b is a giant planet which was discovered by MOA, OGLE and the Wise Observatory. These observatories form a network and conduct a second generation microlensing survey. The survey aims to discover and characterize extrasolar planets and their frequency, by means of round-the-clock high-cadence monitoring of a large area of the Galactic bulge.</description>
	<new />
	<image />
	<imagedescription />
	<list>Confirmed planets</list>
</planet>
