<planet>
	<id_exoplaneteu>OGLE-2013-BLG-0341L B b</id_exoplaneteu>
	<name>OGLE-2013-BLG-0341L B b</name>
	<id>OGLE-2013-BLG-0341L B b</id>
	<discoverymethod>microlensing</discoverymethod>
	<properties>
		<mass>0.005223</mass>
		<radius />
		<orbit>
			<period />
			<semimajoraxis />
			<eccentricity />
			<inclination />
			<periastron />
			<longitude />
			<ascendingnode />
		</orbit>
	</properties>
	<star>
		<spectraltype />
		<mass>0.1209</mass>
		<radius />
		<metallicity />
		<distance>911</distance>
		<temperature />
		<rightascension>17 52 07.49</rightascension>
		<declination>-29 50 46.0</declination>
		<angulardistance />
		<magV />
		<magI />
		<magH />
		<magJ />
		<magK />
	</star>
	<multiplicity>1</multiplicity>
	<discoveryyear>2014</discoveryyear>
	<lastupdate>18/09/18</lastupdate>
	<description>The planet OGLE-20130BLG-0341LB b was discovered with the gravitational microlensing method. The planet is orbiting a star with a very low luminosity. That is why even though the planet's semimajor axis is smaller than that of Earth, its temperature is well below freezing.</description>
	<new />
	<image />
	<imagedescription />
	<list>Confirmed planets</list>
	<list>Planets in binary systems, S-type</list>
</planet>
