<databases>
	<database>
		<name>systems</name>
		<description>Confirmed, controversial and retracted exoplanets</description>
		<num>2017</num>
		<systems>1227</systems>
		<date>2015-06-08</date>
		<size>2566189</size>
		<sizecompressed>318091</sizecompressed>
		<hash>bf116087c032da401d7c8999ef0cb374</hash>
	</database>
	<database>
		<name>systemskepler</name>
		<description>Kepler Objects of Interest (unconfirmed)</description>
		<num>3839</num>
		<systems>2954</systems>
		<date>2015-06-08</date>
		<size>4289232</size>
		<sizecompressed>401073</sizecompressed>
		<hash>23ce0f9504e35783c6abae47393b9981</hash>
	</database>
</databases>
